cloverapi/__init__.py
cloverapi/cloverapi_auth.py
cloverapi/cloverapi_client.py
cloverapi/helpers/__init__.py
cloverapi/helpers/creator.py
cloverapi/helpers/date_helper.py
cloverapi/helpers/http_helper.py
cloverapi/helpers/logging_helper.py
cloverapi/processor/__init__.py
cloverapi/processor/cash_processor.py
cloverapi/processor/inventory_processor.py
cloverapi/processor/order_processor.py
cloverapi/reports/__init__.py
cloverapi/reports/cash_reports.py
cloverapi/reports/inventory_report.py
cloverapi/reports/order_reports.py
cloverapi/services/__init__.py
cloverapi/services/app_service.py
cloverapi/services/cash_service.py
cloverapi/services/customer_service.py
cloverapi/services/employee_service.py
cloverapi/services/inventory_service.py
cloverapi/services/merchant_service.py
cloverapi/services/notification_service.py
cloverapi/services/order_service.py
cloverapi/services/payment_service.py
cloverapi/services/tax_service.py
clover_api_py-0.0.33.dist-info/LICENSE.txt
clover_api_py-0.0.33.dist-info/METADATA
clover_api_py-0.0.33.dist-info/WHEEL
clover_api_py-0.0.33.dist-info/top_level.txt
clover_api_py-0.0.33.dist-info/RECORD
