Metadata-Version: 2.1
Name: clover-api-py
Version: 0.0.33
Summary: An unofficial Python client for the Clover API v3
Home-page: https://github.com/NateDemi/clover-api-py
Download-URL: https://github.com//NateDemi/clover-api-py/archive/refs/heads/main.zip
Author: Nathan Demi
Author-email: ndemissie88@gmail.com
License: MIT
Keywords: clover,api
Classifier: Development Status :: 5 - Production/Stable
Classifier: Intended Audience :: Developers
Classifier: Intended Audience :: Financial and Insurance Industry
Classifier: Intended Audience :: Information Technology
Classifier: Topic :: Software Development :: Libraries :: Python Modules
Classifier: License :: OSI Approved :: MIT License
Classifier: Programming Language :: Python :: 2
Classifier: Programming Language :: Python :: 2.6
Classifier: Programming Language :: Python :: 2.7
Classifier: Programming Language :: Python :: 3
Classifier: Programming Language :: Python :: 3.3
Classifier: Programming Language :: Python :: 3.4
Classifier: Programming Language :: Python :: 3.5
License-File: LICENSE.txt
Requires-Dist: requests>=2.20.0
Requires-Dist: python-dateutil>=2.9.0
Requires-Dist: python-dotenv>=1.0.1
